{
  "place": "Alpine borough, New Jersey, New Jersey",
  "town": "Alpine borough",
  "state": "New Jersey",
  "region": "New Jersey",
  "country": "United States",
  "slug": "alpine-borough-new-jersey-new-jersey",
  "sources": [
    {
      "label": "Wikipedia",
      "url": "https://en.wikipedia.org/wiki/Borough_(New_Jersey)"
    },
    {
      "label": "Web source 1",
      "url": "https://www.bergencountyclerk.gov/HistoricDocuments/alpine"
    },
    {
      "label": "Web source 2",
      "url": "https://www.citydirectory.us/borough-alpine-new-jersey.html"
    }
  ],
  "facts": [
    {
      "id": 1,
      "text": "Alpine was incorporated April 8, 1903, carved from Harrington Township.",
      "sourceSentenceIds": [
        1
      ],
      "sourceLabels": [
        "Web source 1"
      ],
      "source": "https://www.bergencountyclerk.gov/HistoricDocuments/alpine"
    },
    {
      "id": 2,
      "text": "The borough’s name honors Charles Nordhoff’s wife, whose Swiss‑Alpine scenery inspired the title.",
      "sourceSentenceIds": [
        23
      ],
      "sourceLabels": [
        "Web source 1"
      ],
      "source": "https://www.bergencountyclerk.gov/HistoricDocuments/alpine"
    },
    {
      "id": 3,
      "text": "In 1904 Alpine annexed a slice of neighboring Cresskill, expanding its borders.",
      "sourceSentenceIds": [
        22
      ],
      "sourceLabels": [
        "Web source 1"
      ],
      "source": "https://www.bergencountyclerk.gov/HistoricDocuments/alpine"
    },
    {
      "id": 4,
      "text": "Alpine’s historic poster, preserved by the Bergen County Clerk, chronicles its early days.",
      "sourceSentenceIds": [
        1
      ],
      "sourceLabels": [
        "Web source 1"
      ],
      "source": "https://www.bergencountyclerk.gov/HistoricDocuments/alpine"
    },
    {
      "id": 5,
      "text": "Bergen County hosts 56 boroughs, making Alpine part of the state’s largest borough cluster.",
      "sourceSentenceIds": [
        11
      ],
      "sourceLabels": [
        "Wikipedia"
      ],
      "source": "https://en.wikipedia.org/wiki/Borough_(New_Jersey)"
    },
    {
      "id": 6,
      "text": "The 1897 Borough Act required legislative approval for new boroughs, a rule Alpine followed when it was formed.",
      "sourceSentenceIds": [
        14
      ],
      "sourceLabels": [
        "Wikipedia"
      ],
      "source": "https://en.wikipedia.org/wiki/Borough_(New_Jersey)"
    }
  ]
}