{
  "place": "Anderson CDP, New Jersey, New Jersey",
  "town": "Anderson CDP",
  "state": "New Jersey",
  "region": "New Jersey",
  "country": "United States",
  "slug": "anderson-cdp-new-jersey-new-jersey",
  "sources": [
    {
      "label": "Wikipedia",
      "url": "https://en.wikipedia.org/wiki/Leonardo%2C_New_Jersey"
    },
    {
      "label": "Web source 1",
      "url": "https://newjersey.hometownlocator.com/nj/warren/anderson.cfm"
    },
    {
      "label": "Web source 2",
      "url": "https://uspopulation.org/new-jersey/warren-county/anderson-cdp/"
    }
  ],
  "facts": [
    {
      "id": 1,
      "text": "Leonardo was named for Henry and James Leonard, the first ironmasters of New Jersey.",
      "sourceSentenceIds": [
        2
      ],
      "sourceLabels": [
        "Wikipedia"
      ],
      "source": "https://en.wikipedia.org/wiki/Leonardo%2C_New_Jersey"
    },
    {
      "id": 2,
      "text": "The Quick Stop convenience store on Leonard Avenue was the filming location for Kevin Smith’s 1994 movie Clerks.",
      "sourceSentenceIds": [
        5
      ],
      "sourceLabels": [
        "Wikipedia"
      ],
      "source": "https://en.wikipedia.org/wiki/Leonardo%2C_New_Jersey"
    },
    {
      "id": 3,
      "text": "In 1958 an Ajax missile exploded at the Nike missile base in Leonardo, killing ten people.",
      "sourceSentenceIds": [
        11
      ],
      "sourceLabels": [
        "Wikipedia"
      ],
      "source": "https://en.wikipedia.org/wiki/Leonardo%2C_New_Jersey"
    },
    {
      "id": 4,
      "text": "Since the Nike program ended in 1974, the former launch base has been turned into single‑family homes.",
      "sourceSentenceIds": [
        12
      ],
      "sourceLabels": [
        "Wikipedia"
      ],
      "source": "https://en.wikipedia.org/wiki/Leonardo%2C_New_Jersey"
    },
    {
      "id": 5,
      "text": "Leonardo sits on the south shore of Raritan Bay, part of New Jersey’s Jersey Shore region.",
      "sourceSentenceIds": [
        9
      ],
      "sourceLabels": [
        "Wikipedia"
      ],
      "source": "https://en.wikipedia.org/wiki/Leonardo%2C_New_Jersey"
    }
  ]
}