{
  "place": "Chautauqua CDP, New York, New York",
  "town": "Chautauqua CDP",
  "state": "New York",
  "region": "New York",
  "country": "United States",
  "slug": "chautauqua-cdp-new-york-new-york",
  "sources": [
    {
      "label": "Wikipedia",
      "url": "https://en.wikipedia.org/wiki/Chautauqua_County%2C_New_York"
    },
    {
      "label": "Web source 1",
      "url": "https://chautauquacountyny.gov/county-historian/resources"
    },
    {
      "label": "Web source 2",
      "url": "https://www.tourchautauqua.com/learn/history-and-culture"
    }
  ],
  "facts": [
    {
      "id": 1,
      "text": "Chautauqua County’s streets echo the Underground Railroad, where local abolitionists hid escaped slaves seeking freedom.",
      "sourceSentenceIds": [
        1
      ],
      "sourceLabels": [
        "Web source 1"
      ],
      "source": "https://chautauquacountyny.gov/county-historian/resources"
    },
    {
      "id": 2,
      "text": "In 1871, the Fisk Jubilee Singers graced Jamestown’s stage, bringing powerful spirituals to packed crowds and marking a historic tour.",
      "sourceSentenceIds": [
        2
      ],
      "sourceLabels": [
        "Web source 1"
      ],
      "source": "https://chautauquacountyny.gov/county-historian/resources"
    },
    {
      "id": 3,
      "text": "Charles Kolb’s article on the Erie Indians reveals Chautauqua’s last pre‑contact inhabitants, blending myth and fact.",
      "sourceSentenceIds": [
        4
      ],
      "sourceLabels": [
        "Web source 1"
      ],
      "source": "https://chautauquacountyny.gov/county-historian/resources"
    },
    {
      "id": 4,
      "text": "The Trolley 98 Restoration Project revives a historic Jamestown streetcar, spotlighting the county’s transportation heritage.",
      "sourceSentenceIds": [
        5
      ],
      "sourceLabels": [
        "Web source 1"
      ],
      "source": "https://chautauquacountyny.gov/county-historian/resources"
    },
    {
      "id": 5,
      "text": "During the 1850s, Chautauqua became a national hub for hammered dulcimer production, crafting thousands in local workshops.",
      "sourceSentenceIds": [
        12
      ],
      "sourceLabels": [
        "Web source 1"
      ],
      "source": "https://chautauquacountyny.gov/county-historian/resources"
    },
    {
      "id": 6,
      "text": "The Chautauqua Institution, founded in the late 19th century, remains a cultural beacon for lectures, performances, and summer programs.",
      "sourceSentenceIds": [
        9
      ],
      "sourceLabels": [
        "Web source 2"
      ],
      "source": "https://www.tourchautauqua.com/learn/history-and-culture"
    }
  ]
}