{
  "place": "Endicott, New York",
  "town": "Endicott",
  "state": "New York",
  "region": "New York",
  "country": "United States",
  "slug": "endicott-new-york",
  "sources": [
    {
      "label": "Wikipedia",
      "url": "https://en.wikipedia.org/wiki/Endicott%2C_New_York"
    },
    {
      "label": "Web source 1",
      "url": "https://www.endicottny.com/history/"
    },
    {
      "label": "Web source 2",
      "url": "https://endicotthistory.org/"
    }
  ],
  "facts": [
    {
      "id": 1,
      "text": "Endicott was founded as a company town by the Endicott-Johnson Corporation, becoming the largest shoe company worldwide by WWI.",
      "sourceSentenceIds": [
        12
      ],
      "sourceLabels": [
        "Wikipedia"
      ],
      "source": "https://en.wikipedia.org/wiki/Endicott%2C_New_York"
    },
    {
      "id": 2,
      "text": "The village was named in honor of Henry B. Endicott, a Massachusetts shoemaker who bought the company in 1890.",
      "sourceSentenceIds": [
        10
      ],
      "sourceLabels": [
        "Web source 1"
      ],
      "source": "https://www.endicottny.com/history/"
    },
    {
      "id": 3,
      "text": "In 1911, the Computing-Tabulating-Recording Company, later IBM, was founded in Endicott, launching a century of tech innovation.",
      "sourceSentenceIds": [
        9
      ],
      "sourceLabels": [
        "Wikipedia"
      ],
      "source": "https://en.wikipedia.org/wiki/Endicott%2C_New_York"
    },
    {
      "id": 4,
      "text": "The Endicott History & Heritage Center, run by the Old Village of Union Historical Society, showcases extensive displays on both EJ and IBM.",
      "sourceSentenceIds": [
        5
      ],
      "sourceLabels": [
        "Web source 2"
      ],
      "source": "https://endicotthistory.org/"
    },
    {
      "id": 5,
      "text": "During World War II, several IBM factories in Endicott were converted to produce sidearm pistols for the war effort.",
      "sourceSentenceIds": [
        17
      ],
      "sourceLabels": [
        "Wikipedia"
      ],
      "source": "https://en.wikipedia.org/wiki/Endicott%2C_New_York"
    },
    {
      "id": 6,
      "text": "The village’s historic business district sits at the intersection of NYS Route 26 and NYS Route 17C, once the original Union village center.",
      "sourceSentenceIds": [
        11
      ],
      "sourceLabels": [
        "Wikipedia"
      ],
      "source": "https://en.wikipedia.org/wiki/Endicott%2C_New_York"
    }
  ]
}
