{
  "place": "Ives Estates, Florida",
  "town": "Ives Estates",
  "state": "Florida",
  "region": "Florida",
  "country": "United States",
  "slug": "ives-estates-florida",
  "sources": [
    {
      "label": "Wikipedia",
      "url": "https://en.wikipedia.org/wiki/Ives_Estates%2C_Florida"
    },
    {
      "label": "Web source 1",
      "url": "https://florida.hometownlocator.com/fl/miami-dade/ives-estates.cfm"
    },
    {
      "label": "Web source 2",
      "url": "https://movesllc.com/ives-estates-fl/"
    }
  ],
  "facts": [
    {
      "id": 1,
      "text": "Ives Estates sits within the Miami metropolitan area of South Florida.",
      "sourceSentenceIds": [
        6
      ],
      "sourceLabels": [
        "Wikipedia"
      ],
      "source": "https://en.wikipedia.org/wiki/Ives_Estates%2C_Florida"
    },
    {
      "id": 2,
      "text": "The community lies in northeastern Miami‑Dade, touching Broward County to the north.",
      "sourceSentenceIds": [
        7
      ],
      "sourceLabels": [
        "Wikipedia"
      ],
      "source": "https://en.wikipedia.org/wiki/Ives_Estates%2C_Florida"
    },
    {
      "id": 3,
      "text": "County Road 854, also known as Ives Dairy Road, cuts through Ives Estates and links Aventura to Miami Gardens.",
      "sourceSentenceIds": [
        11
      ],
      "sourceLabels": [
        "Wikipedia"
      ],
      "source": "https://en.wikipedia.org/wiki/Ives_Estates%2C_Florida"
    },
    {
      "id": 4,
      "text": "Ives Estates Park serves as the neighborhood’s hub, offering sports fields and hosting community events.",
      "sourceSentenceIds": [
        4
      ],
      "sourceLabels": [
        "Web source 2"
      ],
      "source": "https://movesllc.com/ives-estates-fl/"
    },
    {
      "id": 5,
      "text": "Madie Ives K‑8 Preparatory Academy, a public school, carries the community’s namesake and serves local students.",
      "sourceSentenceIds": [
        27
      ],
      "sourceLabels": [
        "Wikipedia"
      ],
      "source": "https://en.wikipedia.org/wiki/Ives_Estates%2C_Florida"
    },
    {
      "id": 6,
      "text": "The area’s history mirrors the broader development of Miami‑Dade County, reflecting its growth over time.",
      "sourceSentenceIds": [
        3
      ],
      "sourceLabels": [
        "Web source 2"
      ],
      "source": "https://movesllc.com/ives-estates-fl/"
    }
  ]
}
