{
  "place": "Jan, Phyl Florida",
  "town": "Jan",
  "state": "Phyl Florida",
  "region": "Phyl Florida",
  "country": "United States",
  "slug": "jan-phyl-florida",
  "sources": [
    {
      "label": "Wikipedia",
      "url": "https://en.wikipedia.org/wiki/Jan_Phyl_Village%2C_Florida"
    },
    {
      "label": "Web source 1",
      "url": "https://www.floridasmart.com/city-guide/jan-phyl-village"
    },
    {
      "label": "Web source 2",
      "url": "https://www.city-data.com/city/Jan-Phyl-Village-Florida.html"
    }
  ],
  "facts": [
    {
      "id": 1,
      "text": "Jan Phyl Village was founded in 1950 by Jacob C., who envisioned a tight‑knit community for plant workers.",
      "sourceSentenceIds": [
        1
      ],
      "sourceLabels": [
        "Web source 1"
      ],
      "source": "https://www.floridasmart.com/city-guide/jan-phyl-village"
    },
    {
      "id": 2,
      "text": "The community’s name comes from Harry Lesnick’s daughters, Janet and Phyllis, honoring their family legacy.",
      "sourceSentenceIds": [
        6,
        7
      ],
      "sourceLabels": [
        "Wikipedia"
      ],
      "source": "https://en.wikipedia.org/wiki/Jan_Phyl_Village%2C_Florida"
    },
    {
      "id": 3,
      "text": "It began as a planned residential area for workers at a nearby plant, offering affordable homes just minutes from the factory.",
      "sourceSentenceIds": [
        2
      ],
      "sourceLabels": [
        "Web source 1"
      ],
      "source": "https://www.floridasmart.com/city-guide/jan-phyl-village"
    },
    {
      "id": 4,
      "text": "With its rich history, strong community spirit, and scenic lakes, Jan Phyl Village is considered one of Polk County’s hidden treasures.",
      "sourceSentenceIds": [
        4
      ],
      "sourceLabels": [
        "Web source 1"
      ],
      "source": "https://www.floridasmart.com/city-guide/jan-phyl-village"
    },
    {
      "id": 5,
      "text": "A planned transportation improvement could widen major roads by 2030 to handle growing traffic, according to the Polk Transportation Planning Organization.",
      "sourceSentenceIds": [
        11
      ],
      "sourceLabels": [
        "Wikipedia"
      ],
      "source": "https://en.wikipedia.org/wiki/Jan_Phyl_Village%2C_Florida"
    },
    {
      "id": 6,
      "text": "Just southwest of Winter Haven along Spirit Lake Road, Jan Phyl Village sits in the Central Florida Region’s quiet suburban stretch.",
      "sourceSentenceIds": [
        25
      ],
      "sourceLabels": [
        "Web source 1"
      ],
      "source": "https://www.floridasmart.com/city-guide/jan-phyl-village"
    }
  ]
}
