{
  "place": "Lake Worth Beach, Florida",
  "town": "Lake Worth Beach",
  "state": "Florida",
  "region": "Florida",
  "country": "United States",
  "slug": "lake-worth-beach-florida",
  "sources": [
    {
      "label": "Wikipedia",
      "url": "https://en.wikipedia.org/wiki/Lake_Worth_Beach%2C_Florida"
    },
    {
      "label": "Web source 1",
      "url": "https://lakeworthbeachfl.gov/"
    },
    {
      "label": "Web source 2",
      "url": "https://www.floridavisiting.com/list/lake-worth/"
    }
  ],
  "facts": [
    {
      "id": 1,
      "text": "Lake Worth Beach’s name comes from the lagoon named after General William J. Worth.",
      "sourceSentenceIds": [
        9
      ],
      "sourceLabels": [
        "Wikipedia"
      ],
      "source": "https://en.wikipedia.org/wiki/Lake_Worth_Beach%2C_Florida"
    },
    {
      "id": 2,
      "text": "The Lake Worth Playhouse, built in 1953, began as the Oakley Theatre and remains a historic downtown landmark.",
      "sourceSentenceIds": [
        2,
        11
      ],
      "sourceLabels": [
        "Web source 2",
        "Wikipedia"
      ],
      "source": "https://www.floridavisiting.com/list/lake-worth/"
    },
    {
      "id": 3,
      "text": "The city’s public library, a Mediterranean‑style building completed in 1941, cost $66,000 and sits at 15 North M Street.",
      "sourceSentenceIds": [
        15
      ],
      "sourceLabels": [
        "Wikipedia"
      ],
      "source": "https://en.wikipedia.org/wiki/Lake_Worth_Beach%2C_Florida"
    },
    {
      "id": 4,
      "text": "Lake Worth Community College, founded in 1933 as Palm Beach Junior College, is Florida’s oldest community college.",
      "sourceSentenceIds": [
        13
      ],
      "sourceLabels": [
        "Wikipedia"
      ],
      "source": "https://en.wikipedia.org/wiki/Lake_Worth_Beach%2C_Florida"
    },
    {
      "id": 5,
      "text": "The Lake Worth Water, Light, and Ice Company, established in 1914 for 600 residents, now serves about 27,000 customers.",
      "sourceSentenceIds": [
        18
      ],
      "sourceLabels": [
        "Wikipedia"
      ],
      "source": "https://en.wikipedia.org/wiki/Lake_Worth_Beach%2C_Florida"
    },
    {
      "id": 6,
      "text": "The Lake Worth Historical Museum occupies the second floor of the old city hall, which served as the administrative center from the 1920s to 1973.",
      "sourceSentenceIds": [
        29
      ],
      "sourceLabels": [
        "Wikipedia"
      ],
      "source": "https://en.wikipedia.org/wiki/Lake_Worth_Beach%2C_Florida"
    }
  ]
}
