{
  "place": "Lake Wales, Florida",
  "town": "Lake Wales",
  "state": "Florida",
  "region": "Florida",
  "country": "United States",
  "slug": "lake-wales-florida",
  "sources": [
    {
      "label": "Wikipedia",
      "url": "https://en.wikipedia.org/wiki/Lake_Wales%2C_Florida"
    },
    {
      "label": "Web source 1",
      "url": "https://www.lakewalesfl.gov/396/About-Lake-Wales"
    },
    {
      "label": "Web source 2",
      "url": "https://www.visitflorida.com/places-to-go/central/lake-wales/"
    }
  ],
  "facts": [
    {
      "id": 1,
      "text": "Lake Wales was founded in 1911 by the Lake Wales Land Company after buying 5,000 acres around Lake Wailes.",
      "sourceSentenceIds": [
        1
      ],
      "sourceLabels": [
        "Web source 1"
      ],
      "source": "https://www.lakewalesfl.gov/396/About-Lake-Wales"
    },
    {
      "id": 2,
      "text": "Lake Wailes lake was renamed after Sidney Irving Wailes, a land agent who surveyed the area after the Civil War.",
      "sourceSentenceIds": [
        23
      ],
      "sourceLabels": [
        "Wikipedia"
      ],
      "source": "https://en.wikipedia.org/wiki/Lake_Wales%2C_Florida"
    },
    {
      "id": 3,
      "text": "Bok Tower Gardens, a historic landmark and one of Florida’s most famous botanical gardens, sits in Lake Wales.",
      "sourceSentenceIds": [
        3
      ],
      "sourceLabels": [
        "Web source 2"
      ],
      "source": "https://www.visitflorida.com/places-to-go/central/lake-wales/"
    },
    {
      "id": 4,
      "text": "The Lake Wales History Museum occupies the old Atlantic Coast Line Railroad Depot, a building that once served the 1925 rail line.",
      "sourceSentenceIds": [
        8,
        9,
        7
      ],
      "sourceLabels": [
        "Wikipedia"
      ],
      "source": "https://en.wikipedia.org/wiki/Lake_Wales%2C_Florida"
    },
    {
      "id": 5,
      "text": "Lake Wales celebrates its cowboy roots with annual rodeo events that echo the town’s historic ranching past.",
      "sourceSentenceIds": [
        12
      ],
      "sourceLabels": [
        "Web source 2"
      ],
      "source": "https://www.visitflorida.com/places-to-go/central/lake-wales/"
    }
  ]
}
