{
  "place": "Largo, Florida",
  "town": "Largo",
  "state": "Florida",
  "region": "Florida",
  "country": "United States",
  "slug": "largo-florida",
  "sources": [
    {
      "label": "Wikipedia",
      "url": "https://en.wikipedia.org/wiki/Florida_City%2C_Florida"
    },
    {
      "label": "Web source 1",
      "url": "https://www.largo.com/connect/living_in_largo/largo_city_history/index.php"
    },
    {
      "label": "Web source 2",
      "url": "https://largohistoricalsociety.org/category/local-history/"
    }
  ],
  "facts": [
    {
      "id": 1,
      "text": "In 1886 the Orange Belt Railroad arrived, and residents united to name the new stop Largo.",
      "sourceSentenceIds": [
        12
      ],
      "sourceLabels": [
        "Web source 1"
      ],
      "source": "https://www.largo.com/connect/living_in_largo/largo_city_history/index.php"
    },
    {
      "id": 2,
      "text": "The Tocobaga people were the original inhabitants of the land that became Largo.",
      "sourceSentenceIds": [
        10
      ],
      "sourceLabels": [
        "Web source 1"
      ],
      "source": "https://www.largo.com/connect/living_in_largo/largo_city_history/index.php"
    },
    {
      "id": 3,
      "text": "Jackson’s West Coast Garage, opened around 1935, has served as a cornerstone of Largo’s history for 90 years.",
      "sourceSentenceIds": [
        15,
        16
      ],
      "sourceLabels": [
        "Web source 2"
      ],
      "source": "https://largohistoricalsociety.org/category/local-history/"
    },
    {
      "id": 4,
      "text": "Harbor Bluffs, once part of Largo, grew along the waterfront and now lies in unincorporated Pinellas County.",
      "sourceSentenceIds": [
        17
      ],
      "sourceLabels": [
        "Web source 2"
      ],
      "source": "https://largohistoricalsociety.org/category/local-history/"
    },
    {
      "id": 5,
      "text": "The Largo Historical Society, along with the library and Heritage Village, preserves the city’s archives and regional history.",
      "sourceSentenceIds": [
        2
      ],
      "sourceLabels": [
        "Web source 1"
      ],
      "source": "https://www.largo.com/connect/living_in_largo/largo_city_history/index.php"
    }
  ]
}
