{
  "place": "Lawrenceville CDP, New Jersey, New Jersey",
  "town": "Lawrenceville CDP",
  "state": "New Jersey",
  "region": "New Jersey",
  "country": "United States",
  "slug": "lawrenceville-cdp-new-jersey-new-jersey",
  "sources": [
    {
      "label": "Wikipedia",
      "url": "https://en.wikipedia.org/wiki/Lawrenceville%2C_New_Jersey"
    },
    {
      "label": "Web source 1",
      "url": "https://www.lawrencevillemainstreet.com/history"
    },
    {
      "label": "Web source 2",
      "url": "https://www.lawrencetwp.com/main-street-historic-district"
    }
  ],
  "facts": [
    {
      "id": 1,
      "text": "Founded as Maidenhead in 1697, the village was renamed Lawrenceville the same year in honor of Captain John Lawrence.",
      "sourceSentenceIds": [
        4,
        5,
        8
      ],
      "sourceLabels": [
        "Wikipedia",
        "Web source 1"
      ],
      "source": "https://en.wikipedia.org/wiki/Lawrenceville%2C_New_Jersey"
    },
    {
      "id": 2,
      "text": "Lawrenceville’s Main Street Historic District entered the National Register in 1972, making it one of New Jersey’s first historic districts.",
      "sourceSentenceIds": [
        29
      ],
      "sourceLabels": [
        "Wikipedia"
      ],
      "source": "https://en.wikipedia.org/wiki/Lawrenceville%2C_New_Jersey"
    },
    {
      "id": 3,
      "text": "The Lawrenceville School, founded in 1810, has long served as the village’s dominant economic force.",
      "sourceSentenceIds": [
        6,
        14
      ],
      "sourceLabels": [
        "Wikipedia"
      ],
      "source": "https://en.wikipedia.org/wiki/Lawrenceville%2C_New_Jersey"
    },
    {
      "id": 4,
      "text": "Historic accounts describe Lawrenceville’s streets as possessing a lightness, gaiety, and fragility that set them apart from surrounding homes.",
      "sourceSentenceIds": [
        22
      ],
      "sourceLabels": [
        "Web source 2"
      ],
      "source": "https://www.lawrencetwp.com/main-street-historic-district"
    },
    {
      "id": 5,
      "text": "In 2023 the Jigger Shop moved from the Irwin Dining Center to the newly built Tsai Field House, reflecting campus evolution.",
      "sourceSentenceIds": [
        7
      ],
      "sourceLabels": [
        "Wikipedia"
      ],
      "source": "https://en.wikipedia.org/wiki/Lawrenceville%2C_New_Jersey"
    }
  ]
}