{
  "place": "Livingston Manor, New York",
  "town": "Livingston Manor",
  "state": "New York",
  "region": "New York",
  "country": "United States",
  "slug": "livingston-manor-new-york",
  "sources": [
    {
      "label": "Wikipedia",
      "url": "https://en.wikipedia.org/wiki/Livingston_Manor%2C_New_York"
    },
    {
      "label": "Web source 1",
      "url": "https://livingstonmanorny.com/Our-Town"
    },
    {
      "label": "Web source 2",
      "url": "https://www.iloveny.com/blog/post/48-hours-in-livingston-manor/"
    }
  ],
  "facts": [
    {
      "id": 1,
      "text": "Livingston Manor was formed in 1879 along the Oswego railway line and named after Robert Livingston the Elder.",
      "sourceSentenceIds": [
        1
      ],
      "sourceLabels": [
        "Web source 1"
      ],
      "source": "https://livingstonmanorny.com/Our-Town"
    },
    {
      "id": 2,
      "text": "The community renamed itself Livingston Manor after descendants of the prominent Livingston family.",
      "sourceSentenceIds": [
        3
      ],
      "sourceLabels": [
        "Wikipedia"
      ],
      "source": "https://en.wikipedia.org/wiki/Livingston_Manor%2C_New_York"
    },
    {
      "id": 3,
      "text": "It is the scene of an annual 'trout parade' in June that draws marching bands, fire trucks and other local amusements.",
      "sourceSentenceIds": [
        6
      ],
      "sourceLabels": [
        "Wikipedia"
      ],
      "source": "https://en.wikipedia.org/wiki/Livingston_Manor%2C_New_York"
    },
    {
      "id": 4,
      "text": "Livingston Manor is located in the southern part of the town of Rockland.",
      "sourceSentenceIds": [
        12
      ],
      "sourceLabels": [
        "Wikipedia"
      ],
      "source": "https://en.wikipedia.org/wiki/Livingston_Manor%2C_New_York"
    },
    {
      "id": 5,
      "text": "Numerous times, heavy rain storms increased Willowemoc Creek flow, flooding main street and low areas of the hamlet.",
      "sourceSentenceIds": [
        7
      ],
      "sourceLabels": [
        "Wikipedia"
      ],
      "source": "https://en.wikipedia.org/wiki/Livingston_Manor%2C_New_York"
    }
  ]
}
