{
  "place": "Mount Ivy, New York",
  "town": "Mount Ivy",
  "state": "New York",
  "region": "New York",
  "country": "United States",
  "slug": "mount-ivy-new-york",
  "sources": [
    {
      "label": "Wikipedia",
      "url": "https://en.wikipedia.org/wiki/Mount_Ivy%2C_New_York"
    },
    {
      "label": "Web source 1",
      "url": "https://roadsidethoughts.com/ny/mount-ivy-xx-rockland-profile.htm"
    },
    {
      "label": "Web source 2",
      "url": "https://www.mapsof.net/mount-ivy"
    }
  ],
  "facts": [
    {
      "id": 1,
      "text": "Mount Ivy earned its name from its lofty elevation and nearby ivy swamp.",
      "sourceSentenceIds": [
        11
      ],
      "sourceLabels": [
        "Wikipedia"
      ],
      "source": "https://en.wikipedia.org/wiki/Mount_Ivy%2C_New_York"
    },
    {
      "id": 2,
      "text": "Mount Ivy was once a significant Quaker settlement in the region.",
      "sourceSentenceIds": [
        10
      ],
      "sourceLabels": [
        "Wikipedia"
      ],
      "source": "https://en.wikipedia.org/wiki/Mount_Ivy%2C_New_York"
    },
    {
      "id": 3,
      "text": "For many years, the Ramapough Mountain Indians inhabited the Mount Ivy area.",
      "sourceSentenceIds": [
        9
      ],
      "sourceLabels": [
        "Wikipedia"
      ],
      "source": "https://en.wikipedia.org/wiki/Mount_Ivy%2C_New_York"
    },
    {
      "id": 4,
      "text": "Mount Ivy straddles the boundary between Ramapo and Haverstraw, lying in southern Haverstraw.",
      "sourceSentenceIds": [
        13
      ],
      "sourceLabels": [
        "Wikipedia"
      ],
      "source": "https://en.wikipedia.org/wiki/Mount_Ivy%2C_New_York"
    },
    {
      "id": 5,
      "text": "The business hub sits at the northern end of NY State Route 45, where it meets US.",
      "sourceSentenceIds": [
        14
      ],
      "sourceLabels": [
        "Wikipedia"
      ],
      "source": "https://en.wikipedia.org/wiki/Mount_Ivy%2C_New_York"
    },
    {
      "id": 6,
      "text": "Mount Ivy residents use the Pomona post office for mail services.",
      "sourceSentenceIds": [
        15
      ],
      "sourceLabels": [
        "Wikipedia"
      ],
      "source": "https://en.wikipedia.org/wiki/Mount_Ivy%2C_New_York"
    }
  ]
}
