{
  "place": "New Hartford, New York",
  "town": "New Hartford",
  "state": "New York",
  "region": "New York",
  "country": "United States",
  "slug": "new-hartford-new-york",
  "sources": [
    {
      "label": "Wikipedia",
      "url": "https://en.wikipedia.org/wiki/List_of_municipalities_in_New_York"
    },
    {
      "label": "Web source 1",
      "url": "https://villageofnewhartford.gov/"
    },
    {
      "label": "Web source 2",
      "url": "https://www.newhartfordhistory.com/"
    }
  ],
  "facts": [
    {
      "id": 1,
      "text": "New Hartford village was incorporated in 1870, marking its formal establishment as a local government.",
      "sourceSentenceIds": [
        3
      ],
      "sourceLabels": [
        "Web source 2"
      ],
      "source": "https://www.newhartfordhistory.com/"
    },
    {
      "id": 2,
      "text": "The Town of New Hartford was officially created in 1888 when the Town of Whitestown was divided.",
      "sourceSentenceIds": [
        4
      ],
      "sourceLabels": [
        "Web source 2"
      ],
      "source": "https://www.newhartfordhistory.com/"
    },
    {
      "id": 3,
      "text": "A walking tour that starts at 2 Paris Road guides visitors through historic sites across the village.",
      "sourceSentenceIds": [
        7
      ],
      "sourceLabels": [
        "Web source 2"
      ],
      "source": "https://www.newhartfordhistory.com/"
    },
    {
      "id": 4,
      "text": "The village maintains a Stormwater Management Plan to protect local waterways and manage runoff.",
      "sourceSentenceIds": [
        2
      ],
      "sourceLabels": [
        "Web source 1"
      ],
      "source": "https://villageofnewhartford.gov/"
    },
    {
      "id": 5,
      "text": "New Hartford is celebrated for its heritage, heart, and hospitality, a sentiment echoed by residents and visitors alike.",
      "sourceSentenceIds": [
        19
      ],
      "sourceLabels": [
        "Web source 1"
      ],
      "source": "https://villageofnewhartford.gov/"
    },
    {
      "id": 6,
      "text": "The New Hartford Historical Society’s museum is open year‑round except during the winter months of January through March.",
      "sourceSentenceIds": [
        1
      ],
      "sourceLabels": [
        "Web source 2"
      ],
      "source": "https://www.newhartfordhistory.com/"
    }
  ]
}
