{
  "place": "Ocean Beach, New York",
  "town": "Ocean Beach",
  "state": "New York",
  "region": "New York",
  "country": "United States",
  "slug": "ocean-beach-new-york",
  "sources": [
    {
      "label": "Wikipedia",
      "url": "https://en.wikipedia.org/wiki/Ocean_Beach%2C_New_York"
    },
    {
      "label": "Web source 1",
      "url": "https://villageofoceanbeach.org/"
    },
    {
      "label": "Web source 2",
      "url": "https://www.worldatlas.com/cities/ocean-beach-new-york.html"
    }
  ],
  "facts": [
    {
      "id": 1,
      "text": "Ocean Beach was incorporated as a village in 1921, marking its formal establishment on Fire Island.",
      "sourceSentenceIds": [
        15
      ],
      "sourceLabels": [
        "Wikipedia"
      ],
      "source": "https://en.wikipedia.org/wiki/Ocean_Beach%2C_New_York"
    },
    {
      "id": 2,
      "text": "During the Jazz Age, Ocean Beach became the first gay village on Fire Island, attracting artists and performers from New York City.",
      "sourceSentenceIds": [
        20
      ],
      "sourceLabels": [
        "Wikipedia"
      ],
      "source": "https://en.wikipedia.org/wiki/Ocean_Beach%2C_New_York"
    },
    {
      "id": 3,
      "text": "The village’s strict local ordinances earned it the nickname “The Land of No,” a playful nod to its conservative rules.",
      "sourceSentenceIds": [
        3
      ],
      "sourceLabels": [
        "Wikipedia"
      ],
      "source": "https://en.wikipedia.org/wiki/Ocean_Beach%2C_New_York"
    },
    {
      "id": 4,
      "text": "Ocean Beach hosts Fire Island’s only elementary school, which first opened its doors in 1918.",
      "sourceSentenceIds": [
        18
      ],
      "sourceLabels": [
        "Wikipedia"
      ],
      "source": "https://en.wikipedia.org/wiki/Ocean_Beach%2C_New_York"
    },
    {
      "id": 5,
      "text": "A historic landmark nearby is the Fire Island Lighthouse, standing as a beacon for generations of visitors.",
      "sourceSentenceIds": [
        12
      ],
      "sourceLabels": [
        "Web source 2"
      ],
      "source": "https://www.worldatlas.com/cities/ocean-beach-new-york.html"
    },
    {
      "id": 6,
      "text": "Ocean Beach was established in the early 20th century, originally developing as a small seaside community on Fire Island.",
      "sourceSentenceIds": [
        4
      ],
      "sourceLabels": [
        "Web source 2"
      ],
      "source": "https://www.worldatlas.com/cities/ocean-beach-new-york.html"
    }
  ]
}
