{
  "place": "Poestenkill, New York",
  "town": "Poestenkill",
  "state": "New York",
  "region": "New York",
  "country": "United States",
  "slug": "poestenkill-new-york",
  "sources": [
    {
      "label": "Wikipedia",
      "url": "https://en.wikipedia.org/wiki/Poestenkill_(CDP)%2C_New_York"
    },
    {
      "label": "Web source 1",
      "url": "https://www.poestenkillny.com/history"
    },
    {
      "label": "Web source 2",
      "url": "https://www.newyorkalmanack.com/2021/09/the-poestenkill-mountains-waterfalls-and-waterworks/"
    }
  ],
  "facts": [
    {
      "id": 1,
      "text": "Poestenkill takes its name from the Poesten Kill stream, one of Rensselaer County's most important waterways.",
      "sourceSentenceIds": [
        5,
        9,
        12
      ],
      "sourceLabels": [
        "Web source 1",
        "Wikipedia"
      ],
      "source": "https://www.poestenkillny.com/history"
    },
    {
      "id": 2,
      "text": "In the 1870s the village hosted saw, grist, cotton batten, flax, and shirt mills, fueling early industrial life.",
      "sourceSentenceIds": [
        3,
        2
      ],
      "sourceLabels": [
        "Web source 2",
        "Web source 1"
      ],
      "source": "https://www.newyorkalmanack.com/2021/09/the-poestenkill-mountains-waterfalls-and-waterworks/"
    },
    {
      "id": 3,
      "text": "A diverting dam reduced flow in the Quacken and Poesten kills, hastening abandonment of some mills along both streams.",
      "sourceSentenceIds": [
        7
      ],
      "sourceLabels": [
        "Web source 2"
      ],
      "source": "https://www.newyorkalmanack.com/2021/09/the-poestenkill-mountains-waterfalls-and-waterworks/"
    },
    {
      "id": 4,
      "text": "The town was formed from Sand Lake on March 2, 1848, making it one of Rensselaer's youngest towns.",
      "sourceSentenceIds": [
        26,
        25
      ],
      "sourceLabels": [
        "Web source 1"
      ],
      "source": "https://www.poestenkillny.com/history"
    },
    {
      "id": 5,
      "text": "Poestenkill’s rural heritage is protected by a pledge to preserve scenic beauty and historic assets.",
      "sourceSentenceIds": [
        20
      ],
      "sourceLabels": [
        "Web source 1"
      ],
      "source": "https://www.poestenkillny.com/history"
    },
    {
      "id": 6,
      "text": "Early settlers arrived from Troy, Greenbush, Massachusetts, Connecticut, and the Hudson before the Revolutionary War.",
      "sourceSentenceIds": [
        27
      ],
      "sourceLabels": [
        "Web source 1"
      ],
      "source": "https://www.poestenkillny.com/history"
    }
  ]
}
