{
  "place": "Throgs Neck, Bronx, New York",
  "town": "Throgs Neck",
  "state": "New York",
  "region": "Bronx",
  "country": "United States",
  "slug": "throgs-neck-bronx-new-york",
  "sources": [
    {
      "label": "Wikipedia",
      "url": "https://en.wikipedia.org/wiki/Throggs_Neck"
    },
    {
      "label": "Web source 1",
      "url": "https://www.cityneighborhoods.nyc/throggs-neck"
    },
    {
      "label": "Web source 2",
      "url": "https://urbanareas.net/info/resources/neighborhoods-bronx/throgs-neck-bronx-history/"
    }
  ],
  "facts": [
    {
      "id": 1,
      "text": "Throggs Neck takes its name from 17th‑century settler John Throckmorton, who founded a short‑lived colony there in 1642.",
      "sourceSentenceIds": [
        2,
        11
      ],
      "sourceLabels": [
        "Web source 1",
        "Wikipedia"
      ],
      "source": "https://www.cityneighborhoods.nyc/throggs-neck"
    },
    {
      "id": 2,
      "text": "Fort Schuyler, built between 1833 and 1856 at the peninsula’s tip, later became the New York State Merchant Marine Academy and now houses SUNY Maritime College.",
      "sourceSentenceIds": [
        8,
        14,
        15
      ],
      "sourceLabels": [
        "Web source 1",
        "Web source 1",
        "Web source 1"
      ],
      "source": "https://www.cityneighborhoods.nyc/throggs-neck"
    },
    {
      "id": 3,
      "text": "The peninsula juts into the East River and Long Island Sound, with Westchester Creek forming its western edge and Baisley Avenue marking the north.",
      "sourceSentenceIds": [
        26,
        28,
        29
      ],
      "sourceLabels": [
        "Wikipedia",
        "Wikipedia",
        "Wikipedia"
      ],
      "source": "https://en.wikipedia.org/wiki/Throggs_Neck"
    },
    {
      "id": 4,
      "text": "Throggs Neck Landing, a new ferry stop on the Soundview route, opened on December 28, 2021, linking the peninsula directly to Manhattan.",
      "sourceSentenceIds": [
        22
      ],
      "sourceLabels": [
        "Wikipedia"
      ],
      "source": "https://en.wikipedia.org/wiki/Throggs_Neck"
    },
    {
      "id": 5,
      "text": "Christine Jorgensen, the first transgender celebrity, was born and raised on Dudley Avenue in Throggs Neck during the 1950s and 60s.",
      "sourceSentenceIds": [
        1
      ],
      "sourceLabels": [
        "Wikipedia"
      ],
      "source": "https://en.wikipedia.org/wiki/Throggs_Neck"
    }
  ]
}