{
  "place": "Tokyo, Japan",
  "town": "Tokyo",
  "state": "Japan",
  "region": "Japan",
  "country": "Japan",
  "slug": "tokyo-japan",
  "sources": [
    {
      "label": "Wikipedia",
      "url": "https://en.wikipedia.org/wiki/Tokyo"
    },
    {
      "label": "Web source 1",
      "url": "https://www.gotokyo.org/en/index.html"
    },
    {
      "label": "Web source 2",
      "url": "https://tokyotokyo.jp/home/"
    }
  ],
  "facts": [
    {
      "id": 1,
      "text": "Tokyo was renamed from Edo to Tokyo in 1868 when the imperial capital moved from Kyoto.",
      "sourceSentenceIds": [
        12,
        15,
        21
      ],
      "sourceLabels": [
        "Wikipedia"
      ],
      "source": "https://en.wikipedia.org/wiki/Tokyo"
    },
    {
      "id": 2,
      "text": "Tokyo Station, opened 1914, became the central hub for Japan’s Shinkansen network.",
      "sourceSentenceIds": [
        10,
        28
      ],
      "sourceLabels": [
        "Wikipedia"
      ],
      "source": "https://en.wikipedia.org/wiki/Tokyo"
    },
    {
      "id": 3,
      "text": "Shibuya Crossing, with about 3,000 people at once, is the world’s busiest pedestrian crossing.",
      "sourceSentenceIds": [
        18
      ],
      "sourceLabels": [
        "Wikipedia"
      ],
      "source": "https://en.wikipedia.org/wiki/Tokyo"
    },
    {
      "id": 4,
      "text": "Tokyo hosted the 1964 Summer Olympics, becoming the first Asian city to hold the Games.",
      "sourceSentenceIds": [
        4,
        8,
        25
      ],
      "sourceLabels": [
        "Wikipedia"
      ],
      "source": "https://en.wikipedia.org/wiki/Tokyo"
    },
    {
      "id": 5,
      "text": "The Mitsukoshi department store in Nihombashi, founded in 1673, is Japan’s first department store.",
      "sourceSentenceIds": [
        3
      ],
      "sourceLabels": [
        "Wikipedia"
      ],
      "source": "https://en.wikipedia.org/wiki/Tokyo"
    },
    {
      "id": 6,
      "text": "The annual Short Shorts Film Festival & Asia began in 2026 in Tokyo, showcasing short films worldwide.",
      "sourceSentenceIds": [
        20
      ],
      "sourceLabels": [
        "Web source 1"
      ],
      "source": "https://www.gotokyo.org/en/index.html"
    }
  ]
}
