{
  "place": "West Palm Beach, Florida",
  "town": "West Palm Beach",
  "state": "Florida",
  "region": "Florida",
  "country": "United States",
  "slug": "west-palm-beach-florida",
  "sources": [
    {
      "label": "Wikipedia",
      "url": "https://en.wikipedia.org/wiki/Palm_Beach_Gardens%2C_Florida"
    },
    {
      "label": "Web source 1",
      "url": "https://www.wpb.org/Our-City/History"
    },
    {
      "label": "Web source 2",
      "url": "https://visitwpb.org/"
    }
  ],
  "facts": [
    {
      "id": 1,
      "text": "Clematis Street, West Palm Beach’s heartbeat, lines historic charm, buzzing nightlife, and trendy restaurants.",
      "sourceSentenceIds": [
        13
      ],
      "sourceLabels": [
        "Web source 2"
      ],
      "source": "https://visitwpb.org/"
    },
    {
      "id": 2,
      "text": "Flamingo Park blends history with modern appeal, offering a green oasis in the city.",
      "sourceSentenceIds": [
        14
      ],
      "sourceLabels": [
        "Web source 2"
      ],
      "source": "https://visitwpb.org/"
    },
    {
      "id": 3,
      "text": "West Palm Beach hosts outdoor adventures from tennis courts to pro‑level golf courses and action‑packed water sports.",
      "sourceSentenceIds": [
        9
      ],
      "sourceLabels": [
        "Web source 2"
      ],
      "source": "https://visitwpb.org/"
    },
    {
      "id": 4,
      "text": "The city prepares for hurricane season with Vegetation Amnesty Days from April 27 to May 8, 2026.",
      "sourceSentenceIds": [
        11
      ],
      "sourceLabels": [
        "Web source 1"
      ],
      "source": "https://www.wpb.org/Our-City/History"
    },
    {
      "id": 5,
      "text": "Historic Northwood District preserves West Palm Beach’s deep‑rooted African American history through homes and community spaces.",
      "sourceSentenceIds": [
        19
      ],
      "sourceLabels": [
        "Web source 2"
      ],
      "source": "https://visitwpb.org/"
    },
    {
      "id": 6,
      "text": "The city’s first commercial building permit was issued to RCA in 1960 for a factory, marking the start of industrial growth.",
      "sourceSentenceIds": [
        5
      ],
      "sourceLabels": [
        "Wikipedia"
      ],
      "source": "https://en.wikipedia.org/wiki/Palm_Beach_Gardens%2C_Florida"
    }
  ]
}
